MANIFEST.in
README.rst
setup.cfg
setup.py
tw2/__init__.py
tw2.codemirror.egg-info/PKG-INFO
tw2.codemirror.egg-info/SOURCES.txt
tw2.codemirror.egg-info/dependency_links.txt
tw2.codemirror.egg-info/entry_points.txt
tw2.codemirror.egg-info/namespace_packages.txt
tw2.codemirror.egg-info/not-zip-safe
tw2.codemirror.egg-info/pbr.json
tw2.codemirror.egg-info/requires.txt
tw2.codemirror.egg-info/top_level.txt
tw2/codemirror/__init__.py
tw2/codemirror/samples.py
tw2/codemirror/widgets.py
tw2/codemirror/static/style.css
tw2/codemirror/static/addon/comment/comment.js
tw2/codemirror/static/addon/comment/continuecomment.js
tw2/codemirror/static/addon/dialog/dialog.css
tw2/codemirror/static/addon/dialog/dialog.js
tw2/codemirror/static/addon/display/fullscreen.css
tw2/codemirror/static/addon/display/fullscreen.js
tw2/codemirror/static/addon/display/panel.js
tw2/codemirror/static/addon/display/placeholder.js
tw2/codemirror/static/addon/display/rulers.js
tw2/codemirror/static/addon/edit/closebrackets.js
tw2/codemirror/static/addon/edit/closetag.js
tw2/codemirror/static/addon/edit/continuelist.js
tw2/codemirror/static/addon/edit/matchbrackets.js
tw2/codemirror/static/addon/edit/matchtags.js
tw2/codemirror/static/addon/edit/trailingspace.js
tw2/codemirror/static/addon/fold/brace-fold.js
tw2/codemirror/static/addon/fold/comment-fold.js
tw2/codemirror/static/addon/fold/foldcode.js
tw2/codemirror/static/addon/fold/foldgutter.css
tw2/codemirror/static/addon/fold/foldgutter.js
tw2/codemirror/static/addon/fold/indent-fold.js
tw2/codemirror/static/addon/fold/markdown-fold.js
tw2/codemirror/static/addon/fold/xml-fold.js
tw2/codemirror/static/addon/hint/anyword-hint.js
tw2/codemirror/static/addon/hint/css-hint.js
tw2/codemirror/static/addon/hint/html-hint.js
tw2/codemirror/static/addon/hint/javascript-hint.js
tw2/codemirror/static/addon/hint/show-hint.css
tw2/codemirror/static/addon/hint/show-hint.js
tw2/codemirror/static/addon/hint/sql-hint.js
tw2/codemirror/static/addon/hint/xml-hint.js
tw2/codemirror/static/addon/lint/coffeescript-lint.js
tw2/codemirror/static/addon/lint/css-lint.js
tw2/codemirror/static/addon/lint/javascript-lint.js
tw2/codemirror/static/addon/lint/json-lint.js
tw2/codemirror/static/addon/lint/lint.css
tw2/codemirror/static/addon/lint/lint.js
tw2/codemirror/static/addon/lint/yaml-lint.js
