Metadata-Version: 1.1
Name: tw2.codemirror
Version: 0.2.2
Summary: ToscaWidgets2 widget for CodeMirror, a JavaScript-based source code editor
Home-page: https://github.com/moschlar/tw2.codemirror
Author: Moritz Schlarb
Author-email: mail@moritz-schlarb.de
License: WTFPL-2
Keywords: toscawidgets.widgets
Platform: UNKNOWN
Classifier: Development Status :: 4 - Beta
Classifier: Environment :: Web Environment
Classifier: Environment :: Web Environment :: ToscaWidgets
Classifier: Topic :: Software Development :: Libraries :: Python Modules
Classifier: Topic :: Software Development :: Widget Sets
Classifier: Intended Audience :: Developers
Classifier: Operating System :: OS Independent
Classifier: Programming Language :: Python
